{
  "last_updated": "2026-01-25T12:42:55",
  "display_date": "25/01/2026 12:42",
  "status": "Active",
  "epic_data": {
    "status": "Online",
    "latency": "337ms",
    "current_games": [
      {
        "title": "Rustler - Grand Theft Horse",
        "description": "Torne-se um bandido medieval em um jogo de ação maluco de mundo aberto, cheio de referências da cultura pop. Complete missões insanas, mate heróis, roube cavalos, lute contra guardas, roube camponeses, ouça música de bardo e muito mais! Tudo embalado no estilo de jogo da velha escola!",
        "image": "https://cdn1.epicgames.com/spt-assets/a1324ca83bc543ae8747f8d5a99d777a/rustler--grand-theft-horse-1ukey.jpg",
        "url": "https://store.epicgames.com/p/rustler-grand-theft-horse",
        "price": "$24.99",
        "start_date": "2026-01-22T16:00:00.000Z",
        "end_date": "2026-01-29T16:00:00.000Z"
      }
    ],
    "upcoming_games": [
      {
        "title": "Eternal Threads",
        "description": "Eternal Threads é um jogo de quebra-cabeça para um jogador, em primeira pessoa, baseado em uma história de manipulação, escolha e consequência do tempo.",
        "image": "https://cdn1.epicgames.com/spt-assets/08813e055af64315b8a55b2e521f4e04/eternal-threads-1vm6i.jpg",
        "url": "https://store.epicgames.com/p/a9152a8924cc4e438f0e61106ec02f7d",
        "price": "$19.99",
        "start_date": "2026-02-09T16:00:00.000Z",
        "end_date": "2026-02-23T16:00:00.000Z"
      },
      {
        "title": "Ghostrunner 2",
        "description": "Ghostrunner 2 é um slasher FPP hardcore ambientado em um mundo cyberpunk pós-apocalíptico. Apresentando tudo o que os fãs adoraram em Ghostrunner, além de incríveis lutas contra chefes, nova história interativa, níveis emocionantes de motocicleta, habilidades aprimoradas e mais ação cibernética.",
        "image": "https://cdn1.epicgames.com/offer/708f57aaa04b42ef885be16c8288f0ac/EGS_Ghostrunner2_OneMoreLevel_S1_2560x1440-15845148fae1d0cfd7f3e98c9b3ba6ba",
        "url": "https://store.epicgames.com/p/ghostrunner-2",
        "price": "$39.99",
        "start_date": "2026-02-09T16:00:00.000Z",
        "end_date": "2026-02-23T16:00:00.000Z"
      },
      {
        "title": "Castlevania Anniversary Collection",
        "description": "A Coleção de Aniversário de Castlevania da Konami traça as origens da histórica franquia de vampiros. Está incluído um e-book exclusivo com detalhes fornecidos por desenvolvedores, artistas e outros inspirados no legado de Castlevania, que lança uma nova luz sobre o mundo de Castlevania.",
        "image": "https://cdn1.epicgames.com/spt-assets/1ff2f74ba0ef4019b6905d8abe268819/castlevania-anniversary-collection-yex6f.jpg",
        "url": "https://store.epicgames.com/p/32b3e0adbe0c4399be1874958194f97f",
        "price": "$19.99",
        "start_date": "2026-02-09T16:00:00.000Z",
        "end_date": "2026-02-23T16:00:00.000Z"
      },
      {
        "title": "Monument Valley",
        "description": "Embarque em uma jornada de perdão através de ambientes impossíveis e quebra-cabeças ilusórios. Experimente este jogo meditativo e calmante manipulando monumentos e criando caminhos em evolução para explorar mundos novos, surreais e misteriosos.",
        "image": "https://cdn1.epicgames.com/spt-assets/e56a7411805046d3b5b7253a6e4e0faa/monument-valley-1gys5.jpg",
        "url": "https://store.epicgames.com/p/monument-valley-02",
        "price": "$7.99",
        "start_date": "2026-02-09T16:00:00.000Z",
        "end_date": "2026-02-23T16:00:00.000Z"
      },
      {
        "title": "Monument Valley",
        "description": "Embarque em uma jornada de perdão através de ambientes impossíveis e quebra-cabeças ilusórios. Experimente este jogo meditativo e calmante manipulando monumentos e criando caminhos em evolução para explorar mundos novos, surreais e misteriosos.",
        "image": "https://cdn1.epicgames.com/spt-assets/e56a7411805046d3b5b7253a6e4e0faa/monument-valley-1gys5.jpg",
        "url": "https://store.epicgames.com/p/monument-valley-02",
        "price": "$7.99",
        "start_date": "2026-03-30T15:00:00.000Z",
        "end_date": "2026-04-13T15:00:00.000Z"
      },
      {
        "title": "Definitely Not Fried Chicken",
        "description": "Definitivamente Not Fried Chicken é um simulador de gerenciamento de negócios com um toque especial! Aumente o seu comércio de drogas através de frentes legítimas, gerenciando ambos os lados do negócio. Adquira novos “negócios”, conheça nova clientela, desenvolva narcóticos mais potentes, ganhe muito dinheiro e deixe uma cidade em ruínas!",
        "image": "https://cdn1.epicgames.com/spt-assets/a90fa1ecc6fd41b2b98bc04b40b23c71/definitely-not-fried-chicken-thf6o.png",
        "url": "https://store.epicgames.com/p/6b5b8432768a423f848fd85a61c97623",
        "price": "$24.99",
        "start_date": "2026-01-29T16:00:00.000Z",
        "end_date": "2026-02-05T16:00:00.000Z"
      }
    ],
    "mystery_detected": false
  },
  "items": [
    {
      "id": "https://store.epicgames.com/p/rustler-grand-theft-horse",
      "title": "GRÁTIS: Rustler - Grand Theft Horse",
      "original_title": "Rustler - Grand Theft Horse",
      "image": "https://cdn1.epicgames.com/spt-assets/a1324ca83bc543ae8747f8d5a99d777a/rustler--grand-theft-horse-1ukey.jpg",
      "source_count": 1,
      "reliability": "High",
      "category": "Free Games",
      "date": "2026-01-25",
      "summary": "Torne-se um bandido medieval em um jogo de ação maluco de mundo aberto, cheio de referências da cultura pop. Complete missões insanas, mate heróis, roube cavalos, lute contra guardas, roube camponeses, ouça música de bardo e muito mais! Tudo embalado no estilo de jogo da velha escola!",
      "sources": [
        "Epic Games Store"
      ],
      "url": "https://store.epicgames.com/p/rustler-grand-theft-horse"
    },
    {
      "id": "https://store.epicgames.com/p/a9152a8924cc4e438f0e61106ec02f7d",
      "title": "EM BREVE: Eternal Threads",
      "original_title": "Eternal Threads",
      "image": "https://cdn1.epicgames.com/spt-assets/08813e055af64315b8a55b2e521f4e04/eternal-threads-1vm6i.jpg",
      "source_count": 1,
      "reliability": "High",
      "category": "Release Date",
      "date": "2026-01-25",
      "summary": "Disponível gratuitamente a partir de 09/02. Eternal Threads é um jogo de quebra-cabeça para um jogador, em primeira pessoa, baseado em uma história de manipulação, escolha e consequência do tempo.",
      "sources": [
        "Epic Games Store"
      ],
      "url": "https://store.epicgames.com/p/a9152a8924cc4e438f0e61106ec02f7d"
    },
    {
      "id": "https://store.epicgames.com/p/ghostrunner-2",
      "title": "EM BREVE: Ghostrunner 2",
      "original_title": "Ghostrunner 2",
      "image": "https://cdn1.epicgames.com/offer/708f57aaa04b42ef885be16c8288f0ac/EGS_Ghostrunner2_OneMoreLevel_S1_2560x1440-15845148fae1d0cfd7f3e98c9b3ba6ba",
      "source_count": 1,
      "reliability": "High",
      "category": "Release Date",
      "date": "2026-01-25",
      "summary": "Disponível gratuitamente a partir de 09/02. Ghostrunner 2 é um slasher FPP hardcore ambientado em um mundo cyberpunk pós-apocalíptico. Apresentando tudo o que os fãs adoraram em Ghostrunner, além de incríveis lutas contra chefes, nova história interativa, níveis emocionantes de motocicleta, habilidades aprimoradas e mais ação cibernética.",
      "sources": [
        "Epic Games Store"
      ],
      "url": "https://store.epicgames.com/p/ghostrunner-2"
    },
    {
      "id": "https://store.epicgames.com/p/32b3e0adbe0c4399be1874958194f97f",
      "title": "EM BREVE: Castlevania Anniversary Collection",
      "original_title": "Castlevania Anniversary Collection",
      "image": "https://cdn1.epicgames.com/spt-assets/1ff2f74ba0ef4019b6905d8abe268819/castlevania-anniversary-collection-yex6f.jpg",
      "source_count": 1,
      "reliability": "High",
      "category": "Release Date",
      "date": "2026-01-25",
      "summary": "Disponível gratuitamente a partir de 09/02. A Coleção de Aniversário de Castlevania da Konami traça as origens da histórica franquia de vampiros. Está incluído um e-book exclusivo com detalhes fornecidos por desenvolvedores, artistas e outros inspirados no legado de Castlevania, que lança uma nova luz sobre o mundo de Castlevania.",
      "sources": [
        "Epic Games Store"
      ],
      "url": "https://store.epicgames.com/p/32b3e0adbe0c4399be1874958194f97f"
    },
    {
      "id": "https://store.epicgames.com/p/monument-valley-02",
      "title": "EM BREVE: Monument Valley",
      "original_title": "Monument Valley",
      "image": "https://cdn1.epicgames.com/spt-assets/e56a7411805046d3b5b7253a6e4e0faa/monument-valley-1gys5.jpg",
      "source_count": 1,
      "reliability": "High",
      "category": "Release Date",
      "date": "2026-01-25",
      "summary": "Disponível gratuitamente a partir de 09/02. Embarque em uma jornada de perdão através de ambientes impossíveis e quebra-cabeças ilusórios. Experimente este jogo meditativo e calmante manipulando monumentos e criando caminhos em evolução para explorar mundos novos, surreais e misteriosos.",
      "sources": [
        "Epic Games Store"
      ],
      "url": "https://store.epicgames.com/p/monument-valley-02"
    },
    {
      "id": "https://store.epicgames.com/p/monument-valley-02",
      "title": "EM BREVE: Monument Valley",
      "original_title": "Monument Valley",
      "image": "https://cdn1.epicgames.com/spt-assets/e56a7411805046d3b5b7253a6e4e0faa/monument-valley-1gys5.jpg",
      "source_count": 1,
      "reliability": "High",
      "category": "Release Date",
      "date": "2026-01-25",
      "summary": "Disponível gratuitamente a partir de 30/03. Embarque em uma jornada de perdão através de ambientes impossíveis e quebra-cabeças ilusórios. Experimente este jogo meditativo e calmante manipulando monumentos e criando caminhos em evolução para explorar mundos novos, surreais e misteriosos.",
      "sources": [
        "Epic Games Store"
      ],
      "url": "https://store.epicgames.com/p/monument-valley-02"
    },
    {
      "id": "https://store.epicgames.com/p/6b5b8432768a423f848fd85a61c97623",
      "title": "EM BREVE: Definitely Not Fried Chicken",
      "original_title": "Definitely Not Fried Chicken",
      "image": "https://cdn1.epicgames.com/spt-assets/a90fa1ecc6fd41b2b98bc04b40b23c71/definitely-not-fried-chicken-thf6o.png",
      "source_count": 1,
      "reliability": "High",
      "category": "Release Date",
      "date": "2026-01-25",
      "summary": "Disponível gratuitamente a partir de 29/01. Definitivamente Not Fried Chicken é um simulador de gerenciamento de negócios com um toque especial! Aumente o seu comércio de drogas através de frentes legítimas, gerenciando ambos os lados do negócio. Adquira novos “negócios”, conheça nova clientela, desenvolva narcóticos mais potentes, ganhe muito dinheiro e deixe uma cidade em ruínas!",
      "sources": [
        "Epic Games Store"
      ],
      "url": "https://store.epicgames.com/p/6b5b8432768a423f848fd85a61c97623"
    },
    {
      "id": "https://www.eurogamer.net/are-xbox-and-playground-making-the-right-move-sticking-so-closely-to-fables-history",
      "title": "O Xbox e o Playground estão tomando a decisão certa, mantendo-se tão próximos da história de Fable?",
      "original_title": "Are Xbox and Playground making the right move sticking so closely to Fable's history?",
      "image": "https://assetsio.gnwcdn.com/big-question-fable.jpg?width=690&quality=85&format=jpg&auto=webp",
      "source_count": 1,
      "reliability": "High",
      "category": "News",
      "date": "2026-01-25",
      "summary": "Você acredita que já se passou mais de uma década e meia desde a última Fábula propriamente dita? É uma longa espera para qualquer coisa, mas no mundo dos videogames é uma vida inteira - dos avanços tecnológicos às expectativas do público, as coisas mudaram muito...",
      "sources": [
        "Eurogamer"
      ],
      "url": "https://www.eurogamer.net/are-xbox-and-playground-making-the-right-move-sticking-so-closely-to-fables-history"
    },
    {
      "id": "https://www.techpowerup.com/345599/this-week-in-gaming-week-5",
      "title": "Esta semana em jogos (semana 5)",
      "original_title": "This Week in Gaming (Week 5)",
      "image": "https://tpucdn.com/img/QmiEKFnoMtsBuTc9_thm.jpg",
      "source_count": 1,
      "reliability": "High",
      "category": "Hardware",
      "date": "2026-01-25",
      "summary": "Bem-vindo à última semana de janeiro e finalmente voltamos a uma programação de lançamentos mais normal. Temos um grande lançamento único esta semana, que envolve acampar, escalar e tentar não morrer. Pela primeira vez nesta semana, temos um cenário bastante estranho...",
      "sources": [
        "TechPowerUp"
      ],
      "url": "https://www.techpowerup.com/345599/this-week-in-gaming-week-5"
    },
    {
      "id": "https://www.techpowerup.com/345597/microsoft-provided-private-bitlocker-recovery-keys-to-the-fbi",
      "title": "A Microsoft forneceu chaves privadas de recuperação do BitLocker ao FBI",
      "original_title": "Microsoft Provided Private BitLocker Recovery Keys to the FBI",
      "image": "https://tpucdn.com/img/1o117R2QU6QCr3uy_thm.jpg",
      "source_count": 1,
      "reliability": "High",
      "category": "Hardware",
      "date": "2026-01-25",
      "summary": "A Microsoft confirmou que a empresa atendeu ao pedido do Federal Bureau of Investigation (FBI) dos Estados Unidos para distribuir chaves de criptografia BitLocker para desbloquear dados de clientes em três laptops. De acordo com a Forbes, no início do ano passado o Facebook...",
      "sources": [
        "TechPowerUp"
      ],
      "url": "https://www.techpowerup.com/345597/microsoft-provided-private-bitlocker-recovery-keys-to-the-fbi"
    },
    {
      "id": "https://www.eurogamer.net/a-deep-dive-highguard-showcase-will-finally-give-us-an-in-depth-look-at-the-mysterious-game-but-not-until-release-day",
      "title": "Um showcase de “mergulho profundo” de Highguard finalmente nos dará uma “visão aprofundada” do jogo misterioso… mas não antes do dia do lançamento",
      "original_title": "A \"deep dive\" Highguard showcase will finally give us an \"in-depth look\" at the mysterious game... but not until release day",
      "image": "https://assetsio.gnwcdn.com/Highguard-horseriding.jpg?width=690&quality=85&format=jpg&auto=webp",
      "source_count": 1,
      "reliability": "High",
      "category": "News",
      "date": "2026-01-24",
      "summary": "Highguard está definido para abrir a cortina com uma “visão aprofundada de Highguard direto do estúdio” em 26 de janeiro, que também é o mesmo dia em que o jogo de tiro de heróis de serviço ao vivo gratuito deve ser lançado. Leia mais...",
      "sources": [
        "Eurogamer"
      ],
      "url": "https://www.eurogamer.net/a-deep-dive-highguard-showcase-will-finally-give-us-an-in-depth-look-at-the-mysterious-game-but-not-until-release-day"
    },
    {
      "id": "https://www.eurogamer.net/return-to-silent-hill-director-would-like-to-adapt-another-game-plenty-of-people-are-thinking-im-doing-a-pretty-good-job",
      "title": "O diretor de Return to Silent Hill gostaria de adaptar “outro” jogo: “muita gente está pensando que estou fazendo um ótimo trabalho”",
      "original_title": "Return to Silent Hill director would like to adapt \"another\" game: \"plenty of people are thinking I'm doing a pretty good job\"",
      "image": "https://assetsio.gnwcdn.com/return-to-silent-hill-film.png?width=690&quality=85&format=jpg&auto=webp",
      "source_count": 1,
      "reliability": "High",
      "category": "News",
      "date": "2026-01-24",
      "summary": "Apesar das ameaças de morte que enfrentou quando decidiu trazer a franquia de terror da Konami para a tela grande, o diretor do terceiro filme de Silent Hill, Return to Silent Hill, estaria aberto a adaptar outro jogo para a tela grande. Leia mais...",
      "sources": [
        "Eurogamer"
      ],
      "url": "https://www.eurogamer.net/return-to-silent-hill-director-would-like-to-adapt-another-game-plenty-of-people-are-thinking-im-doing-a-pretty-good-job"
    },
    {
      "id": "https://www.eurogamer.net/this-first-person-horror-game-looks-like-a-blend-of-amnesia-bioshock-and-dishonored-and-its-out-soon",
      "title": "Este jogo de terror em primeira pessoa parece uma mistura de Amnesia, BioShock e Dishonored, e será lançado em breve",
      "original_title": "This first-person horror game looks like a blend of Amnesia, BioShock, and Dishonored, and it's out soon",
      "image": "https://assetsio.gnwcdn.com/LTLOJDyg.png?width=690&quality=85&format=jpg&auto=webp",
      "source_count": 1,
      "reliability": "High",
      "category": "News",
      "date": "2026-01-24",
      "summary": "A Blumhouse Games lançará o próximo jogo de aventura e terror em primeira pessoa da Vermila Studios, Crisol: Theatre of Idols, em 10 de fevereiro. Leia mais...",
      "sources": [
        "Eurogamer"
      ],
      "url": "https://www.eurogamer.net/this-first-person-horror-game-looks-like-a-blend-of-amnesia-bioshock-and-dishonored-and-its-out-soon"
    },
    {
      "id": "https://www.eurogamer.net/the-fallout-76-team-is-looking-into-the-issues-youve-been-having-and-says-a-fix-is-coming-in-the-next-few-weeks",
      "title": "A equipe do Fallout 76 está “investigando” os problemas que você tem enfrentado e diz que uma solução chegará nas próximas semanas",
      "original_title": "The Fallout 76 team is \"looking into\" the issues you've been having and says a fix is coming in the next few weeks",
      "image": "https://assetsio.gnwcdn.com/Fallout-76-Ghoul-character-with-headphones-resting-around-his-neck.jpg?width=690&quality=85&format=jpg&auto=webp",
      "source_count": 1,
      "reliability": "High",
      "category": "News",
      "date": "2026-01-24",
      "summary": "A Bethesda está trabalhando para “abordar alguns dos tópicos que apareceram” após a atualização do Fallout 76 lançada no início desta semana. Leia mais...",
      "sources": [
        "Eurogamer"
      ],
      "url": "https://www.eurogamer.net/the-fallout-76-team-is-looking-into-the-issues-youve-been-having-and-says-a-fix-is-coming-in-the-next-few-weeks"
    },
    {
      "id": "https://www.eurogamer.net/arknights-endfield-is-a-step-above-its-peers-thanks-to-three-core-pillars-action-aesthetics-and-a-really-good-base-building-mechanic",
      "title": "Arknights Endfield está um passo acima de seus concorrentes graças a três pilares principais: ação, estética e... uma mecânica de construção de base realmente boa",
      "original_title": "Arknights Endfield is a step above its peers thanks to three core pillars: action, aesthetics, and... a really good base-building mechanic",
      "image": "https://assetsio.gnwcdn.com/Arknights-Endfield-Codes-Header.jpg?width=690&quality=85&format=jpg&auto=webp",
      "source_count": 1,
      "reliability": "High",
      "category": "News",
      "date": "2026-01-24",
      "summary": "Arknights Endfield é o grande lançamento mais recente no mundo dos jogos gacha e, acredite ou não, parece ser uma experiência genuinamente revigorante. O que o torna tão especial? Bem, para mim tudo se resume a três méritos principais: o estilo, a ação,...",
      "sources": [
        "Eurogamer"
      ],
      "url": "https://www.eurogamer.net/arknights-endfield-is-a-step-above-its-peers-thanks-to-three-core-pillars-action-aesthetics-and-a-really-good-base-building-mechanic"
    },
    {
      "id": "https://www.eurogamer.net/what-weve-been-playing-232",
      "title": "O que estamos brincando - \"Ela não falou nada, mas eu vi que ela viu\"",
      "original_title": "What we've been playing - \"She didn't say anything, but I saw that she saw\"",
      "image": "https://assetsio.gnwcdn.com/vaas-far-cry-3.jpg?width=690&quality=85&format=jpg&auto=webp",
      "source_count": 1,
      "reliability": "High",
      "category": "News",
      "date": "2026-01-24",
      "summary": "Olá e bem-vindo de volta ao nosso artigo regular, onde escrevemos um pouco sobre os jogos que temos jogado. Esta semana, Victoria se esforça ao máximo para impressionar o marido com curiosidades de Far Cry; Marie descobre que deixar as coisas como estão por cinco anos pode...",
      "sources": [
        "Eurogamer"
      ],
      "url": "https://www.eurogamer.net/what-weve-been-playing-232"
    },
    {
      "id": "https://www.techpowerup.com/345538/godeal24-winter-software-super-sale-is-live-great-prices-on-genuine-software",
      "title": "A super promoção de software de inverno GoDeal24 está no ar! Ótimos preços em software genuíno",
      "original_title": "GoDeal24 Winter Software Super Sale is Live! Great Prices on Genuine Software",
      "image": "https://tpucdn.com/img/VJCduJdGhlz6VTfG_thm.jpg",
      "source_count": 1,
      "reliability": "High",
      "category": "Hardware",
      "date": "2026-01-24",
      "summary": "GoDeal24 está aqui com a Super Promoção de Software de Inverno! Obtenha grandes descontos em software genuíno e globalmente válido que você precisa para configurar seu PC ou TI empresarial, minimizando os custos de software para abrir espaço para hardware mais caro. Obtenha o Office 2021 Professional genuíno ...",
      "sources": [
        "TechPowerUp"
      ],
      "url": "https://www.techpowerup.com/345538/godeal24-winter-software-super-sale-is-live-great-prices-on-genuine-software"
    },
    {
      "id": "https://www.techpowerup.com/345576/remedy-narrows-down-control-resonant-launch-to-q2-2026",
      "title": "Remedy restringe o lançamento de ‘Control Resonant’ até o segundo trimestre de 2026",
      "original_title": "Remedy Narrows Down 'Control Resonant' Launch to Q2 2026",
      "image": "https://tpucdn.com/img/35VFsvChdcmFpzYB_thm.jpg",
      "source_count": 1,
      "reliability": "High",
      "category": "Hardware",
      "date": "2026-01-24",
      "summary": "Control Resonant foi revelado anteriormente como a sequência do aclamado jogo de ação narrativa Control. Embora o lançamento em 2026 tenha sido confirmado anteriormente, com Remedy e Annapurna cofinanciando e coproduzindo o jogo, uma janela de lançamento exata não foi anunciada...",
      "sources": [
        "TechPowerUp"
      ],
      "url": "https://www.techpowerup.com/345576/remedy-narrows-down-control-resonant-launch-to-q2-2026"
    },
    {
      "id": "https://www.techpowerup.com/345573/nexus-mods-vortex-to-get-linux-support-in-2026-thanks-to-steam-hardware",
      "title": "Nexus Mods Vortex para obter suporte para Linux em 2026, graças ao hardware Steam",
      "original_title": "Nexus Mods Vortex To Get Linux Support in 2026, Thanks to Steam Hardware",
      "image": "https://tpucdn.com/img/MA9BcO99Twjd7OmK_thm.jpg",
      "source_count": 1,
      "reliability": "High",
      "category": "Hardware",
      "date": "2026-01-24",
      "summary": "Nexus Mods é um dos sites de mod mais prolíficos da Internet, abrigando mods para tudo, desde Skyrim e Fallout New Vegas até Stardew Valley e Subnautica. Embora a plataforma mod possua um aplicativo nativo do Windows, chamado Vortex, o desenvolvimento...",
      "sources": [
        "TechPowerUp"
      ],
      "url": "https://www.techpowerup.com/345573/nexus-mods-vortex-to-get-linux-support-in-2026-thanks-to-steam-hardware"
    },
    {
      "id": "https://www.techpowerup.com/345570/cannonkeys-launches-new-pff-profile-uniform-height-keycaps-for-mechanical-keyboards",
      "title": "CannonKeys lança novas teclas de perfil PFF com altura uniforme para teclados mecânicos",
      "original_title": "CannonKeys Launches New PFF Profile Uniform Height Keycaps for Mechanical Keyboards",
      "image": "https://tpucdn.com/img/jY7hqAvi3bfTVdmx_thm.jpg",
      "source_count": 1,
      "reliability": "High",
      "category": "Hardware",
      "date": "2026-01-24",
      "summary": "CannonKeys acaba de anunciar a disponibilidade de um novo perfil de keycap discreto para entusiastas de teclados personalizados. O perfil PFF - Penguin Flat Foot - projetado pelo prolífico designer Matt3o e comercializado pela CannonKeys e fabricado pela Key...",
      "sources": [
        "TechPowerUp"
      ],
      "url": "https://www.techpowerup.com/345570/cannonkeys-launches-new-pff-profile-uniform-height-keycaps-for-mechanical-keyboards"
    },
    {
      "id": "https://www.eurogamer.net/cyberpunk-2077-vr-mod-creator-removes-works-from-patreon-after-yet-another-dmca-strike",
      "title": "O criador do mod Cyberpunk 2077 VR remove obras do Patreon após mais um ataque DMCA",
      "original_title": "Cyberpunk 2077 VR mod creator removes works from Patreon after yet another DMCA strike",
      "image": "https://assetsio.gnwcdn.com/cyberpunk-parkour-game-ghostrunner-is-getting-a-sequel-1620985690980.jpg?width=690&quality=85&format=jpg&auto=webp",
      "source_count": 1,
      "reliability": "High",
      "category": "News",
      "date": "2026-01-23",
      "summary": "O criador do mod Cyberpunk 2077 VR, bem como de uma variedade de outros mods R.E.A.L VR, retirou seus trabalhos do Patreon após receber outro aviso de DMCA. Desta vez, do desenvolvedor Ghostrunner 505 Games. Leia mais...",
      "sources": [
        "Eurogamer"
      ],
      "url": "https://www.eurogamer.net/cyberpunk-2077-vr-mod-creator-removes-works-from-patreon-after-yet-another-dmca-strike"
    },
    {
      "id": "https://www.eurogamer.net/theres-a-super-mario-galaxy-movie-nintendo-direct-coming-this-sunday",
      "title": "Há um filme Super Mario Galaxy Nintendo Direct chegando neste domingo",
      "original_title": "There's a Super Mario Galaxy Movie Nintendo Direct coming this Sunday",
      "image": "https://assetsio.gnwcdn.com/Mario-and-Luigi-with-fire-in-their-hands-in-Mario-Galaxy-movie.jpg?width=690&quality=85&format=jpg&auto=webp",
      "source_count": 1,
      "reliability": "High",
      "category": "News",
      "date": "2026-01-23",
      "summary": "A Nintendo anunciou um Direct dedicado à sua próxima sequência de filme, The Super Mario Galaxy Movie. Leia mais...",
      "sources": [
        "Eurogamer"
      ],
      "url": "https://www.eurogamer.net/theres-a-super-mario-galaxy-movie-nintendo-direct-coming-this-sunday"
    },
    {
      "id": "https://www.eurogamer.net/big-hops-platforming-history-tomb-raider-galleon-distinct-wonderful",
      "title": "Big Hops usa os grandes nomes da história das plataformas - incluindo Tomb Raider e uma pitada de Galleon - para criar algo distinto e maravilhoso",
      "original_title": "Big Hops uses the greats of platforming history - including Tomb Raider and a dash of Galleon - to create something distinct and wonderful",
      "image": "https://assetsio.gnwcdn.com/big-hops_8979raK.jpg?width=690&quality=85&format=jpg&auto=webp",
      "source_count": 1,
      "reliability": "High",
      "category": "News",
      "date": "2026-01-23",
      "summary": "Big Hops é um jogo de plataforma 3D sobre um sapo, mas também é um jogo de plataforma 3D sobre jogos de plataforma 3D. Isso parece quase inevitável quando se trata do gênero de videogame mais nostálgico. Mas o que destaca Big Hops, eu acho, é o puro entusiasmo...",
      "sources": [
        "Eurogamer"
      ],
      "url": "https://www.eurogamer.net/big-hops-platforming-history-tomb-raider-galleon-distinct-wonderful"
    },
    {
      "id": "https://www.techpowerup.com/345548/abxylute-n6-and-n9c-switch-2-controllers-boast-retro-looks-hall-effect-sticks-and-on-board-macros",
      "title": "Os controladores Abxylute N6 e N9C Switch 2 apresentam aparência retrô, bastões de efeito Hall e macros integradas",
      "original_title": "Abxylute N6 and N9C Switch 2 Controllers Boast Retro Looks, Hall Effect Sticks, and On-Board Macros",
      "image": "https://tpucdn.com/img/kBiVU1lkEMQHOOeC_thm.jpg",
      "source_count": 1,
      "reliability": "High",
      "category": "Hardware",
      "date": "2026-01-23",
      "summary": "Abxylute é conhecida por seus controladores de jogos móveis, com modelos que geralmente apresentam joysticks e gatilhos TMR, e os projetos mais recentes da empresa, que ainda não foram lançados, trazem seus designs e tecnologia para o Nintendo Switch 2. O N9C é um jogo com tema retrô...",
      "sources": [
        "TechPowerUp"
      ],
      "url": "https://www.techpowerup.com/345548/abxylute-n6-and-n9c-switch-2-controllers-boast-retro-looks-hall-effect-sticks-and-on-board-macros"
    },
    {
      "id": "https://www.techpowerup.com/345562/sony-electronics-unveils-linkbuds-clip-open-earbuds",
      "title": "(PR) Sony Electronics lança fones de ouvido LinkBuds Clip Open",
      "original_title": "(PR) Sony Electronics Unveils LinkBuds Clip Open Earbuds",
      "image": "https://tpucdn.com/img/B37ElxryFz0RLT3t_thm.jpg",
      "source_count": 1,
      "reliability": "High",
      "category": "Hardware",
      "date": "2026-01-23",
      "summary": "anunciou sua mais recente inovação em áudio vestível: os LinkBuds Clip Truly Wireless Open Earbuds, novos fones de ouvido de clipe aberto verdadeiramente sem fio que permitem aos usuários curtir sua música e o mundo real ao mesmo tempo, redefinindo como as pessoas ...",
      "sources": [
        "TechPowerUp"
      ],
      "url": "https://www.techpowerup.com/345562/sony-electronics-unveils-linkbuds-clip-open-earbuds"
    },
    {
      "id": "https://www.techpowerup.com/345561/beyond-good-and-evil-2-project-survives-latest-ubisoft-reshuffle",
      "title": "Projeto Beyond Good and Evil 2 sobrevive à última remodelação da Ubisoft",
      "original_title": "Beyond Good and Evil 2 Project Survives Latest Ubisoft Reshuffle",
      "image": "https://tpucdn.com/img/IL9wBJC7IImphuJn_thm.jpg",
      "source_count": 1,
      "reliability": "High",
      "category": "Hardware",
      "date": "2026-01-23",
      "summary": "No início da semana, surgiram rumores sobre vários cancelamentos de projetos na presença internacional da Ubisoft. Um comunicado oficial da empresa pareceu confirmar algumas das informações apresentadas nas notícias. Além disso, o vídeo francês g...",
      "sources": [
        "TechPowerUp"
      ],
      "url": "https://www.techpowerup.com/345561/beyond-good-and-evil-2-project-survives-latest-ubisoft-reshuffle"
    },
    {
      "id": "https://www.techpowerup.com/345560/focus-entertainment-highlights-mio-memories-in-orbits-critical-reception",
      "title": "(PR) Focus Entertainment destaca MIO: Memórias na recepção crítica de Orbit",
      "original_title": "(PR) Focus Entertainment Highlights MIO: Memories in Orbit's Critical Reception",
      "image": "https://tpucdn.com/img/PCD0zpAZyCHCUHaN_thm.jpg",
      "source_count": 1,
      "reliability": "High",
      "category": "Hardware",
      "date": "2026-01-23",
      "summary": "Focus Entertainment e Douze Dixièmes estão comemorando hoje o sucesso crítico de MIO: Memories in Orbit com um trailer totalmente novo. Distinguido por sua impressionante direção de arte e uma trilha sonora original igualmente notável, este metroidvan fabricado na França...",
      "sources": [
        "TechPowerUp"
      ],
      "url": "https://www.techpowerup.com/345560/focus-entertainment-highlights-mio-memories-in-orbits-critical-reception"
    }
  ]
}